osmstats/__init__.py
osmstats/osm_features.py
osmstats/osm_stats.py
osmstats-1.1.dist-info/DESCRIPTION.rst
osmstats-1.1.dist-info/METADATA
osmstats-1.1.dist-info/RECORD
osmstats-1.1.dist-info/WHEEL
osmstats-1.1.dist-info/metadata.json
osmstats-1.1.dist-info/top_level.txt
