Metadata-Version: 2.0
Name: osmstats
Version: 1.1
Summary: Processes OpenStreetMap XML file for deriving statistics
Home-page: https://github.com/PrasannaVenkadesh/osmstats
Author: Prasanna Venkadesh
Author-email: prasmailme@gmail.com
License: UNKNOWN
Platform: UNKNOWN
Classifier: Development Status :: 3 - Alpha
Classifier: Intended Audience :: Developers
Classifier: Topic :: Scientific/Engineering :: Information Analysis
Classifier: License :: OSI Approved :: GNU General Public License (GPL)
Classifier: Programming Language :: Python :: 2.7
Classifier: Programming Language :: Python :: 3.5
Classifier: Programming Language :: Python :: 3.6
Classifier: Programming Language :: Python :: Implementation :: CPython
Requires-Python: >=2.7
Requires-Dist: lxml (==4.1.1)
